compiler_testing_lib/__init__.py
compiler_testing_lib/codecheck.py
compiler_testing_lib/runner.py
compiler_testing_lib/languages/C/v0.0/test001.c
compiler_testing_lib/languages/C/v0.0/test002.c
compiler_testing_lib/languages/C/v0.0/test003.c
compiler_testing_lib/languages/C/v0.0/test004.c
compiler_testing_lib/languages/C/v0.0/test005.c
compiler_testing_lib/languages/C/v0.0/test006.c
compiler_testing_lib/languages/C/v0.0/test007.c
compiler_testing_lib/languages/C/v0.0/test008.c
compiler_testing_lib/languages/C/v0.0/test009.c
compiler_testing_lib/languages/C/v0.0/test010.c
compiler_testing_lib/languages/C/v0.0/test011.c
compiler_testing_lib/languages/C/v0.0/test012.c
compiler_testing_lib/languages/C/v0.0/test013.c
compiler_testing_lib/languages/C/v0.0/test014.c
compiler_testing_lib/languages/C/v0.0/tests.yaml
compiler_testing_lib/languages/C/v1.0/test001.c
compiler_testing_lib/languages/C/v1.0/test002.c
compiler_testing_lib/languages/C/v1.0/test003.c
compiler_testing_lib/languages/C/v1.0/test004.c
compiler_testing_lib/languages/C/v1.0/test005.c
compiler_testing_lib/languages/C/v1.0/test006.c
compiler_testing_lib/languages/C/v1.0/test007.c
compiler_testing_lib/languages/C/v1.0/test008.c
compiler_testing_lib/languages/C/v1.0/test009.c
compiler_testing_lib/languages/C/v1.0/test010.c
compiler_testing_lib/languages/C/v1.0/test011.c
compiler_testing_lib/languages/C/v1.0/test012.c
compiler_testing_lib/languages/C/v1.0/test013.c
compiler_testing_lib/languages/C/v1.0/test014.c
compiler_testing_lib/languages/C/v1.0/tests.yaml
compiler_testing_lib/languages/C/v1.1/test001.c
compiler_testing_lib/languages/C/v1.1/test002.c
compiler_testing_lib/languages/C/v1.1/test003.c
compiler_testing_lib/languages/C/v1.1/test004.c
compiler_testing_lib/languages/C/v1.1/test005.c
compiler_testing_lib/languages/C/v1.1/test006.c
compiler_testing_lib/languages/C/v1.1/test007.c
compiler_testing_lib/languages/C/v1.1/test008.c
compiler_testing_lib/languages/C/v1.1/test009.c
compiler_testing_lib-0.1.13.dist-info/licenses/LICENSE
compiler_testing_lib-0.1.13.dist-info/METADATA
compiler_testing_lib-0.1.13.dist-info/WHEEL
compiler_testing_lib-0.1.13.dist-info/top_level.txt
compiler_testing_lib-0.1.13.dist-info/RECORD
