Metadata-Version: 2.4
Name: compiler-testing-lib
Version: 0.1.13
Summary: A testing library for running language/compiler tests from YAML metadata.
Author: Your Name
Requires-Python: >=3.7
License-File: LICENSE
Requires-Dist: pyyaml
Dynamic: author
Dynamic: description
Dynamic: description-content-type
Dynamic: license-file
Dynamic: requires-dist
Dynamic: requires-python
Dynamic: summary
